o7util/__init__.py
o7util/color.py
o7util/conversion.py
o7util/file_explorer.py
o7util/format.py
o7util/html_report.py
o7util/input.py
o7util/menu.py
o7util/pandas.py
o7util/progressbar.py
o7util/pypi.py
o7util/report.py
o7util/run.py
o7util/search.py
o7util/table.py
o7util/terminal.py
o7util-1.0.0.dist-info/licenses/LICENSE
o7util-1.0.0.dist-info/METADATA
o7util-1.0.0.dist-info/WHEEL
o7util-1.0.0.dist-info/top_level.txt
o7util-1.0.0.dist-info/RECORD
