Metadata-Version: 2.4
Name: o7util
Version: 1.0.0
Summary: A collection of utility functions for Python
Author-email: Philippe Gosselin <phil@o7conseils.com>
License:                                  Apache License
Keywords: python,utility,o7conseils
Classifier: Development Status :: 4 - Beta
Classifier: License :: OSI Approved :: Apache Software License
Classifier: Programming Language :: Python :: 3
Classifier: Programming Language :: Python :: 3.11
Classifier: Programming Language :: Python :: 3.12
Classifier: Programming Language :: Python :: 3.13
Requires-Python: >=3.10
License-File: LICENSE
Requires-Dist: sty>=1.0.6
Provides-Extra: pandas
Requires-Dist: pandas>=2.2; extra == "pandas"
Requires-Dist: openpyxl>=3.1; extra == "pandas"
Provides-Extra: dev
Requires-Dist: pandas>=2.2; extra == "dev"
Requires-Dist: openpyxl>=3.1; extra == "dev"
Requires-Dist: pytest; extra == "dev"
Requires-Dist: pytest-cov; extra == "dev"
Requires-Dist: pytest-mock; extra == "dev"
Requires-Dist: ruff; extra == "dev"
Dynamic: license-file
